web3_balancer/__init__.py
web3_balancer/main.py
web3_balancer-0.1b1.dist-info/LICENSE
web3_balancer-0.1b1.dist-info/METADATA
web3_balancer-0.1b1.dist-info/WHEEL
web3_balancer-0.1b1.dist-info/top_level.txt
web3_balancer-0.1b1.dist-info/RECORD
